duo_auth/__init__.py
duo_auth/admin.py
duo_auth/apps.py
duo_auth/legacy_views.py
duo_auth/middleware.py
duo_auth/models.py
duo_auth/tests.py
duo_auth/urls.py
duo_auth/views.py
duo_auth/migrations/__init__.py
duo_auth/static/css/Duo-Frame.css
duo_auth/static/javascript/Duo-Web-v2.js
duo_auth/templates/duo_auth_form.html
django_duo_auth-1.0.0.dist-info/LICENSE
django_duo_auth-1.0.0.dist-info/METADATA
django_duo_auth-1.0.0.dist-info/WHEEL
django_duo_auth-1.0.0.dist-info/top_level.txt
django_duo_auth-1.0.0.dist-info/RECORD
