Metadata-Version: 2.1
Name: django-duo-auth
Version: 1.0.0
Summary: A Django middleware that adds 2-factor authentication via Duo.
Home-page: https://github.com/Elemnir/django-duo-auth
Author: Adam Howard
Author-email: ahoward0920@gmail.com
Maintainer: Adam Howard
Maintainer-email: ahoward0920@gmail.com
License: BSD 3-clause
Platform: UNKNOWN
Classifier: Development Status :: 4 - Beta
Classifier: Environment :: Web Environment
Classifier: Framework :: Django
Classifier: Framework :: Django :: 2
Classifier: Framework :: Django :: 3
Classifier: Framework :: Django :: 4
Classifier: Intended Audience :: Developers
Classifier: License :: OSI Approved :: BSD License
Classifier: Operating System :: OS Independent
Classifier: Programming Language :: Python
Classifier: Programming Language :: Python :: 3
Classifier: Programming Language :: Python :: 3.7
Classifier: Programming Language :: Python :: 3.8
Classifier: Programming Language :: Python :: 3.9
Classifier: Programming Language :: Python :: 3.10
Classifier: Programming Language :: Python :: 3.11
Classifier: Topic :: Internet :: WWW/HTTP
Classifier: Topic :: Internet :: WWW/HTTP :: Dynamic Content
Classifier: Topic :: System :: Systems Administration :: Authentication/Directory
License-File: LICENSE
Requires-Dist: duo-universal
Provides-Extra: legacy
Requires-Dist: duo-web ; extra == 'legacy'
